kctzstyle_first_package/__init__.py
kctzstyle_first_package/hello.py
kctzstyle_first_package-1.0.1.dist-info/LICENSE
kctzstyle_first_package-1.0.1.dist-info/METADATA
kctzstyle_first_package-1.0.1.dist-info/WHEEL
kctzstyle_first_package-1.0.1.dist-info/top_level.txt
kctzstyle_first_package-1.0.1.dist-info/RECORD
