Metadata-Version: 2.1
Name: kctzstyle-first-package
Version: 1.0.1
Summary: kctzstyle's first package
Home-page: https://github.com/kctzstyle/first-pypi-package/
Author: kctzstyle
Author-email: kctzstyle@gmail.com
License: MIT LICENSE
Platform: UNKNOWN
Requires-Python: >=3
